winrt/_winrt_windows_phone_devices_notification.cp310-win32.pyd
winrt/_winrt_windows_phone_devices_notification.pyi
winrt/windows/phone/devices/notification/__init__.py
winrt/windows/phone/devices/notification/py.typed
winrt_windows_phone_devices_notification-3.1.0.dist-info/METADATA
winrt_windows_phone_devices_notification-3.1.0.dist-info/WHEEL
winrt_windows_phone_devices_notification-3.1.0.dist-info/top_level.txt
winrt_windows_phone_devices_notification-3.1.0.dist-info/RECORD
